packetpy/__init__.py
packetpy/core.py
packetpy-0.1.0.dist-info/licenses/LICENSE
packetpy-0.1.0.dist-info/METADATA
packetpy-0.1.0.dist-info/WHEEL
packetpy-0.1.0.dist-info/top_level.txt
packetpy-0.1.0.dist-info/RECORD
